{
    "code": 0,
    "msg": "",
    "count": 101,
    "data": [
    	{
    		"cv_id": "cv_001",
    		"applicant": "申请人A",
    		"am_condition": "0",
    		"visit_cost": "200",
    		"affair": "吃饭"      
    	},
        {
        	"cv_id": "cv_002",
        	"applicant": "申请人A",
        	"am_condition": "0",
        	"visit_cost": "200",
        	"affair": "吃饭"      
        },
        {
        	"cv_id": "cv_003",
        	"applicant": "申请人A",
        	"am_condition": "1",
        	"visit_cost": "200",
        	"affair": "吃饭"      
        },
        {
        	"cv_id": "cv_004",
        	"applicant": "申请人A",
        	"am_condition": "1",
        	"visit_cost": "200",
        	"affair": "吃饭"      
        },
        {
        	"cv_id": "cv_005",
        	"applicant": "申请人A",
        	"am_condition": "1",
        	"visit_cost": "200",
        	"affair": "吃饭"      
        }
        ]}